jupyter_datatables/__about__.py
jupyter_datatables/__init__.py
jupyter_datatables/config.py
jupyter_datatables/css/jupyter-datatables.css
jupyter_datatables/js/components.js
jupyter_datatables/js/config.js
jupyter_datatables/js/graph-objects.js
jupyter_datatables/js/jupyter-datatables.js
jupyter_datatables/js/toolbar.js
jupyter_datatables/js/tooltips.js
jupyter_datatables-0.3.9.dist-info/LICENSE
jupyter_datatables-0.3.9.dist-info/METADATA
jupyter_datatables-0.3.9.dist-info/WHEEL
jupyter_datatables-0.3.9.dist-info/top_level.txt
jupyter_datatables-0.3.9.dist-info/RECORD
