Metadata-Version: 2.1
Name: jupyter-datatables
Version: 0.3.9
Summary: Jupyter Notebook extension to levarage pandas DataFrames by integrating DataTables JS.
Home-page: https://github.com/CermakM/jupyter-datatables
Author: Marek Cermak
Author-email: macermak@redhat.com
License: MIT
Platform: UNKNOWN
Classifier: Development Status :: 2 - Pre-Alpha
Classifier: Framework :: IPython
Classifier: Framework :: Jupyter
Classifier: License :: OSI Approved :: MIT License
Classifier: Natural Language :: English
Classifier: Operating System :: OS Independent
Classifier: Programming Language :: JavaScript
Classifier: Programming Language :: Python :: 3.6
Classifier: Programming Language :: Python :: 3.7
Classifier: Topic :: Scientific/Engineering :: Visualization
Classifier: Topic :: Utilities
Requires-Python: >=3.6
Requires-Dist: ipython
Requires-Dist: ipykernel
Requires-Dist: pandas (>=0.23.0)
Requires-Dist: scipy
Requires-Dist: jupyter-require (>=0.3.0)
